slize/__init__.py
slize/crf_layer.py
slize/demo.py
slize/evaluate.py
slize/model.py
slize/train.py
slize/utils.py
slize-0.0.21.dist-info/METADATA
slize-0.0.21.dist-info/WHEEL
slize-0.0.21.dist-info/top_level.txt
slize-0.0.21.dist-info/RECORD
