Metadata-Version: 2.1
Name: slize
Version: 0.0.21
Summary: Reusable Intent and Slot-filling tool
Home-page: https://github.com/zeionara/slize
Author: Zeio Nara
Author-email: zeionara@gmail.com
License: UNKNOWN
Platform: UNKNOWN
Classifier: Programming Language :: Python :: 3
Classifier: License :: OSI Approved :: MIT License
Classifier: Operating System :: OS Independent
Requires-Python: >=3.6
